semantickit/__init__.py
semantickit/__pycache__/__init__.cpython-36.pyc
semantickit/app/__init__.py
semantickit/distance/Levenshtein.py
semantickit/distance/__init__.py
semantickit/distance/dict_words.txt
semantickit/distance/jaccard.py
semantickit/distance/soren.py
semantickit/distance/weighted_levenshtein.py
semantickit/distance/__pycache__/__init__.cpython-36.pyc
semantickit/distance/__pycache__/weighted_levenshtein.cpython-36.pyc
semantickit/distance/n_gram/__init__.py
semantickit/distance/n_gram/max_ngram.py
semantickit/distance/n_gram/train_ngram.py
semantickit/distance/n_gram/__pycache__/__init__.cpython-36.pyc
semantickit/distance/n_gram/__pycache__/max_ngram.cpython-36.pyc
semantickit/distance/n_gram/__pycache__/train_ngram.cpython-36.pyc
semantickit/lang/__init__.py
semantickit/lang/wordnet.py
semantickit/lang/__pycache__/wordnet.cpython-36.pyc
semantickit/relatedness/__init__.py
semantickit/relatedness/lesk.py
semantickit/relatedness/lesk_context.py
semantickit/relatedness/lesk_max_overlap.py
semantickit/relatedness/__pycache__/__init__.cpython-36.pyc
semantickit/relatedness/__pycache__/lesk.cpython-36.pyc
semantickit/relatedness/__pycache__/lesk_max_overlap.cpython-36.pyc
semantickit/similarity/__init__.py
semantickit/similarity/chinese_word2vec_similarity.py
semantickit/similarity/googlenews_similarity.py
semantickit/similarity/lda_similarity.py
semantickit/similarity/word2vec_similarity.py
semantickit/similarity/wordnet_hyper_hypo.py
semantickit/similarity/wordnet_similarity.py
semantickit/similarity/__pycache__/__init__.cpython-36.pyc
semantickit/similarity/__pycache__/chinese_word2vec_similarity.cpython-36.pyc
semantickit/similarity/__pycache__/word2vec_similarity.cpython-36.pyc
semantickit/similarity/__pycache__/wordnet_hyper_hypo.cpython-36.pyc
semantickit/similarity/__pycache__/wordnet_similarity.cpython-36.pyc
semantic_kit-0.0.3.dist-info/LICENSE
semantic_kit-0.0.3.dist-info/METADATA
semantic_kit-0.0.3.dist-info/WHEEL
semantic_kit-0.0.3.dist-info/top_level.txt
semantic_kit-0.0.3.dist-info/RECORD
