Metadata-Version: 2.1
Name: semantic-kit
Version: 0.0.3
Summary: A toolkit to estimate semantic similarity or relatedness
Home-page: https://github.com/dhchenx/semantic-kit
Author: Donghua Chen
Author-email: douglaschan@126.com
License: MIT
Project-URL: Bug Reports, https://github.com/dhchenx/semantic-kit/issues
Project-URL: Source, https://github.com/dhchenx/semantic-kit
Keywords: semantic analysis,semantic similarity,semantic relatedness,string similarity
Platform: UNKNOWN
Classifier: Development Status :: 5 - Production/Stable
Classifier: Intended Audience :: Developers
Classifier: Topic :: Software Development :: Build Tools
Classifier: License :: OSI Approved :: MIT License
Classifier: Programming Language :: Python :: 3
Classifier: Programming Language :: Python :: 3.6
Classifier: Programming Language :: Python :: 3.7
Classifier: Programming Language :: Python :: 3.8
Classifier: Programming Language :: Python :: 3.9
Classifier: Programming Language :: Python :: 3 :: Only
Requires-Python: >=3.6, <4
License-File: LICENSE
Requires-Dist: nltk
Requires-Dist: gensim
Requires-Dist: sklearn
Requires-Dist: numpy
Requires-Dist: similarity
Requires-Dist: jieba
Provides-Extra: dev
Requires-Dist: check-manifest ; extra == 'dev'
Provides-Extra: test
Requires-Dist: coverage ; extra == 'test'
